very_simple_kawan/__init__.py
very_simple_kawan/add.py
very_simple_kawan/sub.py
very_simple_kawan/extra/__init__.py
very_simple_kawan/extra/divide.py
very_simple_kawan/extra/multiply.py
very_simple_kawan_1-0.0.5.dist-info/METADATA
very_simple_kawan_1-0.0.5.dist-info/WHEEL
very_simple_kawan_1-0.0.5.dist-info/top_level.txt
very_simple_kawan_1-0.0.5.dist-info/RECORD
